[
    {
       "model":"products.product",
       "pk":1,
       "fields":{
          "name":"Batman",
          "category":8,
          "price":"219.99",
          "sku":"PP2210",
          "description":"Poster from Tim Burton's Batman",
          "feature":"Printed on Gloss - Original print from Warner Bros Studios in 1989",
          "unique_size": "27x40 Inches (One Sheet)",
          "feature2": "Limited stock",
          "stock": 3,
          "has_sizes":false,
          "image_url":"",
          "image":"pp-2210.webp"
       }
    },
    {
      "model":"products.product",
      "pk":2,
      "fields":{
         "name":"Die Hard",
         "category":8,
         "price": 14.99,
         "sku":"PP22102",
         "description":"Orignal poster design from the movie Die Hard",
         "feature":"Printed on satin 200gsm paper",
         "has_sizes":true,
         "image_url":"",
         "image":"pp-22102.webp"
      }
   },
   {
      "model":"products.product",
      "pk":3,
      "fields":{
         "name":"Dune",
         "category":8,
         "price":"14.99",
         "sku":"PP22103",
         "description":"Concept illustration of a poster for the Dune adaptation",
         "feature":"Printed on Matt 220gsm paper",
         "has_sizes":true,
         "image_url":"",
         "image":"pp-22103.webp"
      }
   },
   {
      "model":"products.product",
      "pk":4,
      "fields":{
         "name":"John Wick",
         "category":8,
         "price":"19.99",
         "sku":"PP22104",
         "description":"Poster from the first John Wick film in the franchise",
         "feature":"Printed on satin 200gsm paper",
         "has_sizes":true,
         "image_url":"",
         "image":"pp-22104.webp"
      }
   },
   {
      "model":"products.product",
      "pk":5,
      "fields":{
         "name":"Leon",
         "category":8,
         "price":"49.99",
         "sku":"PP22105",
         "description":"Graphic Design Illustration",
         "feature":"Brilliant original design and print",
         "unique_size":"30x20 Inches",
         "feature2": "This paper is smudge and water-resistant with a smooth, bright white, resin coat. Weight: 68 lb. (252 g/m²)",
         "feature3": "Limited stock",
         "stock": 5,
         "has_sizes":false,
         "image_url":"",
         "image":"pp-22105.webp"
      }
   },
   {
      "model":"products.product",
      "pk":6,
      "fields":{
         "name":"Predator",
         "category":8,
         "price":"129.99",
         "sku":"PP22106",
         "description":"Original poster design from Arnold Schwarzenegger's Predator",
         "feature": "Artwork resized, printed and mounted on canvas",
         "unique_size": "40x25 Inches",
         "feature3": "Limited stock",
         "stock": 1,
         "has_sizes":false,
         "image_url":"",
         "image":"pp-22106.webp",
         "image2_url":"",
         "image2":"pp-221064.webp"
      }
   },
   {
      "model":"products.product",
      "pk":7,
      "fields":{
         "name":"Robocop",
         "category":8,
         "price":"14.99",
         "sku":"PP22107",
         "description":"Poster has been designed to look old for effect",
         "feature":"Printed on satin 200gsm paper",
         "has_sizes":true,
         "image_url":"",
         "image":"pp-22107.webp"
      }
   },
   {
      "model":"products.product",
      "pk":8,
      "fields":{
         "name":"Skyfall",
         "category":8,
         "price":"19.99",
         "sku":"PP22108",
         "description":"Rare poster design for the James Bond movie - Skyfall",
         "feature":"Printed on satin 200gsm paper",
         "has_sizes":true,
         "image_url":"",
         "image":"pp-22108.webp"
      }
   },
   {
      "model":"products.product",
      "pk":9,
      "fields":{
         "name":"Terminator 2",
         "category":8,
         "price":"19.99",
         "sku":"PP22109",
         "description":"Original poster design from Arnold Schwarzenegger's Terminator 2",
         "feature":"Printed on satin 200gsm paper",
         "has_sizes":true,
         "image_url":"",
         "image":"pp-22109.webp"
      }
   },
   {
      "model":"products.product",
      "pk":10,
      "fields":{
         "name":"Jurassic Park",
         "category":9,
         "price":"19.99",
         "sku":"PP221010",
         "description":"Original poster design from Steven Spielberg's Jurassic Park",
         "feature":"Printed on satin 200gsm paper",
         "has_sizes":true,
         "image_url":"",
         "image":"pp-221010.webp"
      }
   },
   {
      "model":"products.product",
      "pk":11,
      "fields":{
         "name":"Nope",
         "category":9,
         "price":"39.99",
         "sku":"PP221011",
         "description":"Original poster design from Jordan Peele's Nope",
         "feature":"Printed on high res satin 230gsm paper, we received these personally from the Universal Pictures studio",
         "unique_size": "27x40 Inches (One Sheet)",
         "feature3": "Limited stock",
         "stock": 5,
         "has_sizes":false,
         "image_url":"",
         "image":"pp-221011.webp"
      }
   },
   {
      "model":"products.product",
      "pk":12,
      "fields":{
         "name":"Bill & Ted",
         "category":9,
         "price":"14.99",
         "sku":"PP221012",
         "description":"Poster has been designed to look old for effect",
         "feature":"Printed on matt 220gsm paper",
         "has_sizes":true,
         "image_url":"",
         "image":"pp-221012.webp"
      }
   },
   {
      "model":"products.product",
      "pk":13,
      "fields":{
         "name":"Fear and Loathing",
         "category":9,
         "price":"14.99",
         "sku":"PP221013",
         "description":"Original poster design from Fear and Loathing in Las Vegas",
         "feature":"Printed on matt 220gsm paper",
         "has_sizes":true,
         "image_url":"",
         "image":"pp-221013.webp"
      }
   },
   {
      "model":"products.product",
      "pk":14,
      "fields":{
         "name":"The Goonies",
         "category":9,
         "price":"14.99",
         "sku":"PP221014",
         "description":"Poster has been designed to look old for effect",
         "feature":"Printed on matt 220gsm paper",
         "has_sizes":true,
         "image_url":"",
         "image":"pp-221014.webp"
      }
   },
   {
      "model":"products.product",
      "pk":15,
      "fields":{
         "name":"Gremlins",
         "category":9,
         "price":"14.99",
         "sku":"PP221015",
         "description":"Poster has been designed to look old for effect",
         "feature":"Printed on matt 220gsm paper",
         "has_sizes":true,
         "image_url":"",
         "image":"pp-221015.webp"
      }
   },
   {
      "model":"products.product",
      "pk":16,
      "fields":{
         "name":"Short Circuit",
         "category":9,
         "price":"14.99",
         "sku":"PP221016",
         "description":"Poster has been designed to look old for effect",
         "feature":"Printed on matt 220gsm paper",
         "has_sizes":true,
         "image_url":"",
         "image":"pp-221016.webp"
      }
   },
   {
      "model":"products.product",
      "pk":17,
      "fields":{
         "name":"Indiana Jones",
         "category":9,
         "price":"19.99",
         "sku":"PP221017",
         "description":"Original poster design from The Temple of Doom",
         "feature":"Printed on satin 200gsm paper",
         "has_sizes":true,
         "image_url":"",
         "image":"pp-221017.webp"
      }
   },
   {
      "model":"products.product",
      "pk":18,
      "fields":{
         "name":"Casino",
         "category":7,
         "price":"19.99",
         "sku":"PP221018",
         "description":"Original poster design from Casino",
         "feature":"Printed on satin 200gsm paper",
         "has_sizes":true,
         "image_url":"",
         "image":"pp-221018.webp"
      }
   },
   {
      "model":"products.product",
      "pk":19,
      "fields":{
         "name":"Drive",
         "category":7,
         "price":"79.99",
         "sku":"PP221019",
         "description":"Original poster design from Ryan Gosling's Drive",
         "feature":"Printed on premium satin 200gsm photo paper, framed in a black frame with white mount",
         "unique_size": "27x40 Inches (One Sheet)",
         "feature3": "Limited stock",
         "stock": 1,
         "has_sizes":false,
         "image_url":"",
         "image":"pp-221019.webp",
         "image2_url":"",
         "image2":"pp-221061.webp"
      }
   },
   {
      "model":"products.product",
      "pk":20,
      "fields":{
         "name":"The Good, the Bad and The Ugly",
         "category":7,
         "price":"19.99",
         "sku":"PP221020",
         "description":"Cannot confirm originality of Poster design",
         "feature":"Printed on satin 200gsm paper",
         "has_sizes":true,
         "image_url":"",
         "image":"pp-221020.webp"
      }
   },
   {
      "model":"products.product",
      "pk":21,
      "fields":{
         "name":"Jaws",
         "category":7,
         "price":"19.99",
         "sku":"PP221021",
         "description":"Original poster design from the cult classic Jaws",
         "feature":"Printed on satin 200gsm paper",
         "has_sizes":true,
         "image_url":"",
         "image":"pp-221021.webp"
      }
   },
   {
      "model":"products.product",
      "pk":22,
      "fields":{
         "name":"Pulp Fiction",
         "category":7,
         "price":"19.99",
         "sku":"PP221022",
         "description":"Original poster design, it has not been edited for effect",
         "feature":"Printed on satin 200gsm paper",
         "has_sizes":true,
         "image_url":"",
         "image":"pp-221022.webp"
      }
   },
   {
      "model":"products.product",
      "pk":23,
      "fields":{
         "name":"Romeo & Juliet",
         "category":7,
         "price":"14.99",
         "sku":"PP221023",
         "description":"Original poster design from Leonardo DiCaprio's Romeo & Juliet",
         "feature":"Printed on matt 220gsm paper",
         "has_sizes":true,
         "image_url":"",
         "image":"pp-221023.webp"
      }
   },
   {
      "model":"products.product",
      "pk":24,
      "fields":{
         "name":"Scarface",
         "category":7,
         "price":"14.99",
         "sku":"PP221024",
         "description":"Original poster design from Al Pacino's cult classic, Scarface",
         "feature":"Printed on matt 220gsm paper",
         "has_sizes":true,
         "image_url":"",
         "image":"pp-221024.webp"
      }
   },
   {
      "model":"products.product",
      "pk":25,
      "fields":{
         "name":"Star Wars",
         "category":7,
         "price":"14.99",
         "sku":"PP221025",
         "description":"Star Wars Episode 4 poster",
         "feature":"Printed on matt 220gsm paper",
         "feature2": "Artist: Greg Hildebrandt",
         "has_sizes":true,
         "image_url":"",
         "image":"pp-221025.webp"
      }
   },
   {
      "model":"products.product",
      "pk":26,
      "fields":{
         "name":"True Romance",
         "category":7,
         "price":"14.99",
         "sku":"PP221026",
         "description":"Original poster design from tony Scott and Quentin Tarantino's True Romance",
         "feature":"Printed on matt 220gsm paper",
         "has_sizes":true,
         "image_url":"",
         "image":"pp-221026.webp"
      }
   },
   {
      "model":"products.product",
      "pk":27,
      "fields":{
         "name":"Afro Samurai",
         "category":4,
         "price":"14.99",
         "sku":"PP221027",
         "description":"Afro Samurai is a Japanese seinen dōjinshi manga series",
         "feature":"Printed on matt 220gsm paper",
         "feature2": "Written and illustrated by Takashi Okazaki",
         "has_sizes":true,
         "image_url":"",
         "image":"pp-221027.webp"
      }
   },
   {
      "model":"products.product",
      "pk":28,
      "fields":{
         "name":"Rocket Racoon",
         "category":4,
         "price":"19.99",
         "sku":"PP221028",
         "description":"Fictional character from the Marvel Comics and leader of The Guardians of the Galaxy",
         "feature":"Printed on satin 200gsm paper",
         "feature2":"",
         "has_sizes":true,
         "image_url":"",
         "image":"pp-221028.webp"
      }
   },
   {
      "model":"products.product",
      "pk":29,
      "fields":{
         "name":"Superman",
         "category":4,
         "price":"14.99",
         "sku":"PP221029",
         "description":"Vintage styled illustration of Superman from the DC comics",
         "feature":"Printed on matt 220gsm paper",
         "feature2":"",
         "has_sizes":true,
         "image_url":"",
         "image":"pp-221029.webp"
      }
   },
   {
      "model":"products.product",
      "pk":30,
      "fields":{
         "name":"Thor vs Gorr",
         "category":4,
         "price":"69.99",
         "sku":"PP221030",
         "description":"The mighty Thor fighting Gorr the God Butcher from the Marvel comics",
         "feature": "Photo of the original comic book artwork resized, printed and mounted on canvas",
         "unique_size": "40x25 Inches",
         "feature3": "Limited stock",
         "stock": 2,
         "has_sizes":false,
         "image_url":"",
         "image":"pp-221030.webp",
         "image2_url":"",
         "image2":"pp-221063.webp"
      }
   },
   {
      "model":"products.product",
      "pk":31,
      "fields":{
         "name":"Batman",
         "category":4,
         "price":"19.99",
         "sku":"PP221031",
         "description":"The Dark Knght aka Batman from the DC comics",
         "feature":"Printed on satin 200gsm paper",
         "feature2":"",
         "has_sizes":true,
         "image_url":"",
         "image":"pp-221031.webp"
      }
   },
   {
      "model":"products.product",
      "pk":32,
      "fields":{
         "name":"Naruto",
         "category":4,
         "price":"19.99",
         "sku":"PP221032",
         "description":"Naruto, from the Japanese manga series Naruto",
         "feature":"Printed on satin 200gsm paper",
         "feature2":"Illustrated by Masashi Kishimoto",
         "has_sizes":true,
         "image_url":"",
         "image":"pp-221032.webp"
      }
   },
   {
      "model":"products.product",
      "pk":33,
      "fields":{
         "name":"Marilyn",
         "category":5,
         "price":"19.99",
         "sku":"PP221033",
         "description":"Digital, colourful illustration of Marilyn Monroe",
         "feature":"Printed on satin 200gsm paper",
         "feature2":"",
         "has_sizes":true,
         "image_url":"",
         "image":"pp-221033.webp"
      }
   },
   {
      "model":"products.product",
      "pk":34,
      "fields":{
         "name":"Elephant",
         "category":5,
         "price":"14.99",
         "sku":"PP221034",
         "description":"Line drawing of an elephant",
         "feature":"Printed on high gloss 190gsm paper",
         "feature2":"",
         "has_sizes":true,
         "image_url":"",
         "image":"pp-221034.webp"
      }
   },
   {
      "model":"products.product",
      "pk":35,
      "fields":{
         "name":"Owl",
         "category":5,
         "price":"29.99",
         "sku":"PP221035",
         "description":"Graphic design illustration of an Owl",
         "feature":"Printed on matt 220gsm paper, framed in a black frame with white mount",
         "unique_size":"A3 (279x420mm)",
         "feature3":"Artist: Jamie Letts",
         "stock": 10,
         "has_sizes":false,
         "image_url":"",
         "image":"pp-221035.webp",
         "image2_url":"",
         "image2":"pp-221062.webp"
      }
   },
   {
      "model":"products.product",
      "pk":36,
      "fields":{
         "name":"Cheeky Chappy",
         "category":5,
         "price":"14.99",
         "sku":"PP221036",
         "description":"Graphic design illustration of a boy smoking a cigarette",
         "feature":"Printed on matt 220gsm paper",
         "feature2":"Artist: Jamie Letts",
         "has_sizes":true,
         "image_url":"",
         "image":"pp-221036.webp"
      }
   },
   {
      "model":"products.product",
      "pk":37,
      "fields":{
         "name":"A quiet Place",
         "category":5,
         "price":"19.99",
         "sku":"PP221037",
         "description":"Abstract graphic design illustration",
         "feature":"Printed on satin 200gsm paper",
         "feature2":"",
         "has_sizes":true,
         "image_url":"",
         "image":"pp-221037.webp"
      }
   },
   {
      "model":"products.product",
      "pk":38,
      "fields":{
         "name":"Dream Big!",
         "category":6,
         "price":"19.99",
         "sku":"PP221038",
         "description":"Creative motivational typogpraphy",
         "feature":"Printed on satin 200gsm paper",
         "feature2":"Artist: Gleb Guralnyk",
         "has_sizes":true,
         "image_url":"",
         "image":"pp-221038.webp"
      }
   },
   {
      "model":"products.product",
      "pk":39,
      "fields":{
         "name":"All will be OK",
         "category":6,
         "price":"19.99",
         "sku":"PP221039",
         "description":"Creative motivational typogpraphy",
         "feature":"Printed on satin 200gsm paper",
         "feature2":"",
         "has_sizes":true,
         "image_url":"",
         "image":"pp-221039.webp"
      }
   },
   {
      "model":"products.product",
      "pk":40,
      "fields":{
         "name":"You will succeed!",
         "category":6,
         "price":"14.99",
         "sku":"PP221040",
         "description":"Creative motivational typogpraphy",
         "feature":"Printed on matt 220gsm paper",
         "feature2":"",
         "has_sizes":true,
         "image_url":"Artist: artmonkey",
         "image":"pp-221040.webp"
      }
   },
   {
      "model":"products.product",
      "pk":41,
      "fields":{
         "name":"Stage Door",
         "category":6,
         "price":"14.99",
         "sku":"PP221041",
         "description":"Theatre related creative motivational typogpraphy",
         "feature":"Printed on matt 220gsm paper",
         "feature2":"Artist: Jamie Letts",
         "has_sizes":true,
         "image_url":"",
         "image":"pp-221041.webp"
      }
   },
   {
      "model":"products.product",
      "pk":42,
      "fields":{
         "name":"Night Lights",
         "category":2,
         "price":"19.99",
         "sku":"PP221042",
         "description":"Neon evening light in Kowloon, Hong Kong",
         "feature":"Printed on satin 200gsm paper",
         "feature2":"Photographer: Airam Dato-on",
         "has_sizes":true,
         "image_url":"",
         "image":"pp-221042.webp"
      }
   },
   {
      "model":"products.product",
      "pk":43,
      "fields":{
         "name":"St. Paul's Cathedral",
         "category":2,
         "price":"19.99",
         "sku":"PP221043",
         "description":"St. Paul's Cathedral, London, England",
         "feature":"Printed on satin 200gsm paper",
         "feature2":"Photographer: Andrea De Santis",
         "has_sizes":true,
         "image_url":"",
         "image":"pp-221043.webp"
      }
   },
   {
      "model":"products.product",
      "pk":44,
      "fields":{
         "name":"Blue Skyline",
         "category":2,
         "price":"19.99",
         "sku":"PP221044",
         "description":"Empire State Building, New York City, New York",
         "feature":"Printed on satin 200gsm paper",
         "feature2":"Photographer: Frederik Sørensen",
         "has_sizes":true,
         "image_url":"",
         "image":"pp-221044.webp"
      }
   },
   {
      "model":"products.product",
      "pk":45,
      "fields":{
         "name":"Taj Mahal",
         "category":2,
         "price":"19.99",
         "sku":"PP221045",
         "description":"The Taj Mahal, New Deli, India",
         "feature":"Printed on satin 200gsm paper",
         "feature2":"Photographer: Fuzail Ahmad",
         "has_sizes":true,
         "image_url":"",
         "image":"pp-221045.webp"
      }
   },
   {
      "model":"products.product",
      "pk":46,
      "fields":{
         "name":"Beauty in Colour",
         "category":2,
         "price":"19.99",
         "sku":"PP221046",
         "description":"Colourful architectural design, Portugal",
         "feature":"Printed on satin 200gsm paper",
         "feature2":"Photographer: Fuzail Ahmad",
         "has_sizes":true,
         "image_url":"",
         "image":"pp-221046.webp"
      }
   },
   {
      "model":"products.product",
      "pk":47,
      "fields":{
         "name":"Under the Stars",
         "category":2,
         "price":"19.99",
         "sku":"PP221047",
         "description":"New York City skyline under the moonlight, NEw York",
         "feature":"Printed on satin 200gsm paper",
         "feature2":"Photographer: Piccinng",
         "has_sizes":true,
         "image_url":"",
         "image":"pp-221047.webp"
      }
   },
   {
      "model":"products.product",
      "pk":48,
      "fields":{
         "name":"Good Morning",
         "category":1,
         "price":"19.99",
         "sku":"PP221048",
         "description":"Sunkissed mountain top behind a lake",
         "feature":"Printed on satin 200gsm paper",
         "feature2":"Photographer: Chris Czermak",
         "has_sizes":true,
         "image_url":"",
         "image":"pp-221048.webp"
      }
   },
   {
      "model":"products.product",
      "pk":49,
      "fields":{
         "name":"Field of Lavender",
         "category":1,
         "price":"19.99",
         "sku":"PP221049",
         "description":"Lavender flower field under a pink sky",
         "feature":"Printed on satin 200gsm paper",
         "feature2":"Photographer: David Bartus",
         "has_sizes":true,
         "image_url":"",
         "image":"pp-221049.webp"
      }
   },
   {
      "model":"products.product",
      "pk":50,
      "fields":{
         "name":"Calm of the Night",
         "category":1,
         "price":"19.99",
         "sku":"PP221050",
         "description":"Moonlit wooden dock leading to a still lake, Whistler, BC, Canada",
         "feature":"Printed on satin 200gsm paper",
         "feature2":"Photographer: James Wheeler",
         "has_sizes":true,
         "image_url":"",
         "image":"pp-221050.webp"
      }
   },
   {
      "model":"products.product",
      "pk":51,
      "fields":{
         "name":"Golden Forest",
         "category":1,
         "price":"19.99",
         "sku":"PP221051",
         "description":"Beautiful forest view during sunrise",
         "feature":"Printed on satin 200gsm paper",
         "feature2":"Photographer: Min An",
         "has_sizes":true,
         "image_url":"",
         "image":"pp-221051.webp"
      }
   },
   {
      "model":"products.product",
      "pk":52,
      "fields":{
         "name":"Empty Highway",
         "category":1,
         "price":"19.99",
         "sku":"PP221052",
         "description":"Empty highway overlooking mountains under dark skies, USA",
         "feature":"Printed on satin 200gsm paper",
         "feature2":"Photographer: Sebastian Palomino",
         "has_sizes":true,
         "image_url":"",
         "image":"pp-221052.webp"
      }
   },
   {
      "model":"products.product",
      "pk":53,
      "fields":{
         "name":"Mountain Dawn",
         "category":1,
         "price":"19.99",
         "sku":"PP221053",
         "description":"Mountain view with a pink sky, Brixen im Thale, Tirol, Austria",
         "feature":"Printed on satin 200gsm paper",
         "feature2":"Photographer: Stephan Seeber",
         "has_sizes":true,
         "image_url":"",
         "image":"pp-221053.webp"
      }
   },
   {
      "model":"products.product",
      "pk":54,
      "fields":{
         "name":"Curious Fox",
         "category":3,
         "price":"19.99",
         "sku":"PP221054",
         "description":"Curious looking fox sitting on the ground",
         "feature":"Printed on satin 200gsm paper",
         "feature2":"Photographer: Alex Andrews",
         "has_sizes":true,
         "image_url":"",
         "image":"pp-221054.webp"
      }
   },
   {
      "model":"products.product",
      "pk":55,
      "fields":{
         "name":"The King",
         "category":3,
         "price":"19.99",
         "sku":"PP221055",
         "description":"A male lion's face and mane",
         "feature":"Printed on satin 200gsm paper",
         "feature2":"Photographer: Alexas Fotos",
         "has_sizes":true,
         "image_url":"",
         "image":"pp-221055.webp"
      }
   },
   {
      "model":"products.product",
      "pk":56,
      "fields":{
         "name":"Little Fella",
         "category":3,
         "price":"17.99",
         "sku":"PP221056",
         "description":"A baby monkey sits on a tree branch",
         "feature":"Printed on satin 200gsm paper, award winning photographer, DSD",
         "unique_size": "20x16 Inches",
         "feature3": "Limited stock",
         "stock": 2,
         "has_sizes":false,
         "image_url":"",
         "image":"pp-221056.webp"
      }
   },
   {
      "model":"products.product",
      "pk":57,
      "fields":{
         "name":"Blue Ocean",
         "category":3,
         "price":"19.99",
         "sku":"PP221057",
         "description":"Beatiful under water view of a turle in the ocean",
         "feature":"Printed on satin 200gsm paper",
         "feature2":"Photographer: Francesco Ungaro",
         "has_sizes":true,
         "image_url":"",
         "image":"pp-221057.webp"
      }
   },
   {
      "model":"products.product",
      "pk":58,
      "fields":{
         "name":"Flock of Pink",
         "category":3,
         "price":"19.99",
         "sku":"PP221058",
         "description":"A flock of flamingos with a dark backdrop",
         "feature":"Printed on satin 200gsm paper",
         "feature2":"Photographer: Marko Blazevic",
         "has_sizes":true,
         "image_url":"",
         "image":"pp-221058.webp"
      }
   },
   {
      "model":"products.product",
      "pk":59,
      "fields":{
         "name":"Summer Splash",
         "category":3,
         "price":"19.99",
         "sku":"PP221059",
         "description":"Sunkissed horses gallop through the sea water",
         "feature":"Printed on satin 200gsm paper",
         "feature2":"Photographer: Pixabay",
         "has_sizes":true,
         "image_url":"",
         "image":"pp-221059.webp"
      }
   },
   {
      "model":"products.product",
      "pk":60,
      "fields":{
         "name":"Richmond Stag",
         "category":3,
         "price":"19.99",
         "sku":"PP221060",
         "description":"Stag in the long grass, Richmond Park, London, England",
         "feature":"Printed on satin 200gsm paper",
         "feature2":"Photographer: Yoss Traore",
         "has_sizes":true,
         "image_url":"",
         "image":"pp-221060.webp"
      }
   }
]